hello/__init__.py
fff-0.0.1.dist-info/METADATA
fff-0.0.1.dist-info/WHEEL
fff-0.0.1.dist-info/top_level.txt
fff-0.0.1.dist-info/RECORD
