Metadata-Version: 2.1
Name: fff
Version: 0.0.1
Summary: a minimal example package (pure python version)
Home-page: UNKNOWN
Author: The scikit-build team
Author-email: UNKNOWN
License: MIT
Platform: UNKNOWN
